arya_api_framework/__init__.py
arya_api_framework/constants.py
arya_api_framework/errors.py
arya_api_framework/framework.py
arya_api_framework/models.py
arya_api_framework/utils.py
arya_api_framework/async_framework/__init__.py
arya_api_framework/async_framework/utils.py
arya_api_framework/sync_framework/__init__.py
arya_api_framework/sync_framework/utils.py
arya_api_framework-0.3.9.dist-info/LICENSE
arya_api_framework-0.3.9.dist-info/METADATA
arya_api_framework-0.3.9.dist-info/WHEEL
arya_api_framework-0.3.9.dist-info/top_level.txt
arya_api_framework-0.3.9.dist-info/RECORD
