Metadata-Version: 2.1
Name: arya-api-framework
Version: 0.3.9
Summary: A simple API framework used in many other API clients I create.
Home-page: https://github.com/Aryathel/ApiFramework
Author: Aryathel
License: MIT
Project-URL: Documentation, https://apiframework.readthedocs.io/en/latest/
Classifier: License :: OSI Approved :: MIT License
Classifier: Intended Audience :: Developers
Classifier: Natural Language :: English
Classifier: Operating System :: OS Independent
Classifier: Programming Language :: Python :: 3.10
Requires-Python: >=3.10.0
License-File: LICENSE
Requires-Dist: pydantic (>=1.9.1)
Requires-Dist: yarl (>=1.7.2)
Provides-Extra: async
Requires-Dist: aiohttp (>=3.8.1) ; extra == 'async'
Requires-Dist: aiolimiter (>=1.0.0) ; extra == 'async'
Requires-Dist: aiofiles (>=0.8.0) ; extra == 'async'
Provides-Extra: sync
Requires-Dist: requests (>=2.27.1) ; extra == 'sync'
Requires-Dist: ratelimit (>=2.2.1) ; extra == 'sync'
